LICENSE
MANIFEST.in
README.txt
pytest_figleaf.py
setup.py
test_pytest_figleaf.py
pytest_figleaf.egg-info/PKG-INFO
pytest_figleaf.egg-info/SOURCES.txt
pytest_figleaf.egg-info/dependency_links.txt
pytest_figleaf.egg-info/entry_points.txt
pytest_figleaf.egg-info/not-zip-safe
pytest_figleaf.egg-info/requires.txt
pytest_figleaf.egg-info/top_level.txt